Metadata-Version: 2.1
Name: diffusers-api
Version: 0.0.1
Summary: diffusers-api: A Python API for Diffusion Models
Home-page: https://github.com/kadirnar/diffusers-api
Author: kadirnar
License: Apache License 2.0
Keywords: machine-learning,deep-learning,pytorch,diffusion,diffusion models,controlnet,stable diffusion
Classifier: Development Status :: 5 - Production/Stable
Classifier: Operating System :: OS Independent
Classifier: Intended Audience :: Developers
Classifier: Intended Audience :: Science/Research
Classifier: Programming Language :: Python :: 3
Classifier: Programming Language :: Python :: 3.7
Classifier: Programming Language :: Python :: 3.8
Classifier: Programming Language :: Python :: 3.9
Classifier: Topic :: Software Development :: Libraries
Classifier: Topic :: Software Development :: Libraries :: Python Modules
Classifier: Topic :: Education
Classifier: Topic :: Scientific/Engineering
Classifier: Topic :: Scientific/Engineering :: Artificial Intelligence
Requires-Python: >=3.8
License-File: LICENSE
